next_gen_ui_llama_stack/__init__.py
next_gen_ui_llama_stack/agent.py
next_gen_ui_llama_stack/llama_stack_inference.py
next_gen_ui_llama_stack/types.py
next_gen_ui_llama_stack-0.3.0.dist-info/METADATA
next_gen_ui_llama_stack-0.3.0.dist-info/WHEEL
next_gen_ui_llama_stack-0.3.0.dist-info/namespace_packages.txt
next_gen_ui_llama_stack-0.3.0.dist-info/top_level.txt
next_gen_ui_llama_stack-0.3.0.dist-info/RECORD
