Metadata-Version: 2.1
Name: next_gen_ui_llama_stack
Version: 0.3.0
Summary: Llama-stack integration for Next Gen UI Agent
Home-page: https://github.com/RedHat-UX/next-gen-ui-agent
License: Apache-2.0
Classifier: Programming Language :: Python :: 3
Classifier: Programming Language :: Python :: 3.12
Classifier: Programming Language :: Python :: 3.13
Classifier: License :: OSI Approved :: Apache Software License
Requires-Python: <3.14,>=3.12
Requires-Dist: fire
Requires-Dist: llama-stack-client>=0.2.15
Requires-Dist: next-gen-ui-agent==0.3.0
Requires-Dist: overrides
Requires-Dist: requests
Requires-Dist: typing-extensions
